linkedin/__init__.py
linkedin/exceptions.py
linkedin/linkedin.py
linkedin/models.py
linkedin/server.py
linkedin/utils.py
python3_linkedin-1.0.2.dist-info/DESCRIPTION.rst
python3_linkedin-1.0.2.dist-info/METADATA
python3_linkedin-1.0.2.dist-info/RECORD
python3_linkedin-1.0.2.dist-info/WHEEL
python3_linkedin-1.0.2.dist-info/metadata.json
python3_linkedin-1.0.2.dist-info/top_level.txt
