Metadata-Version: 1.1
Name: python3-linkedin
Version: 1.0.2
Summary: Python Interface to the LinkedIn API
Home-page: https://github.com/DEKHTIARJonathan/python3-linkedin
Author: Jonathan Dekhtiar
Author-email: contact@jonathandekhtiar.eu
License: MIT
Keywords: linkedin python python3
Platform: UNKNOWN
Classifier: Development Status :: 5 - Production/Stable
Classifier: Environment :: Console
Classifier: Intended Audience :: Developers
Classifier: License :: OSI Approved :: MIT License
Classifier: Operating System :: OS Independent
Classifier: Programming Language :: Python :: 2
Classifier: Programming Language :: Python :: 2.7
Classifier: Programming Language :: Python :: 3
Classifier: Programming Language :: Python :: 3.4
Classifier: Programming Language :: Python :: 3.5
Classifier: Programming Language :: Python :: 3.6
Classifier: Natural Language :: English
